endstone_ip_tracker/__init__.py
endstone_ip_tracker/plugin.py
endstone_ip_tracker-0.1.0.dist-info/METADATA
endstone_ip_tracker-0.1.0.dist-info/WHEEL
endstone_ip_tracker-0.1.0.dist-info/entry_points.txt
endstone_ip_tracker-0.1.0.dist-info/licenses/LICENSE
endstone_ip_tracker-0.1.0.dist-info/RECORD
