Metadata-Version: 2.4
Name: endstone-ip-tracker
Version: 0.1.0
Summary: Python IP tracker plugin for Endstone servers
Project-URL: Homepage, https://github.com/your-username/endstone-ip-tracker
Author-email: Tsing_loong <tsingloong611@gmail.com>
License: MIT License
License-File: LICENSE
Keywords: endstone,ip,plugin,tracker
